setup.cfg
setup.py
kooft_api/_init_.py
kooft_api/kooft.py
kooft_api.egg-info/PKG-INFO
kooft_api.egg-info/SOURCES.txt
kooft_api.egg-info/dependency_links.txt
kooft_api.egg-info/not-zip-safe
kooft_api.egg-info/top_level.txt