Metadata-Version: 1.0
Name: kooft-api
Version: 0.5
Summary: Kooft API
Home-page: UNKNOWN
Author: UNKNOWN
Author-email: likel0vsky@gmail.com
License: UNKNOWN
Platform: UNKNOWN
